{
    "skins": [
        {
            "id": "default",
            "name": "Default",
            "color": "#00ffff",
            "type": "free",
            "glowColor": "rgba(0, 255, 255, 0.5)",
            "borderColor": "rgba(0, 255, 255, 0.3)",
            "cost": 0
        },
        {
            "id": "neon",
            "name": "Neon",
            "color": "#9966ff",
            "type": "free",
            "glowColor": "rgba(153, 102, 255, 0.5)",
            "borderColor": "rgba(153, 102, 255, 0.3)",
            "cost": 0
        },
        {
            "id": "golden",
            "name": "Golden",
            "color": "#ffd700",
            "type": "premium",
            "glowColor": "rgba(255, 215, 0, 0.5)",
            "borderColor": "rgba(255, 215, 0, 0.3)",
            "cost": 2000
        },
        {
            "id": "rainbow",
            "name": "Rainbow",
            "color": "#00ffaa",
            "type": "premium",
            "glowColor": "rgba(0, 255, 170, 0.5)",
            "borderColor": "rgba(0, 255, 170, 0.3)",
            "cost": 3000,
            "special": "rainbow"
        },
        {
            "id": "cosmic",
            "name": "Cosmic",
            "color": "#ff66aa",
            "type": "premium",
            "glowColor": "rgba(255, 102, 170, 0.5)",
            "borderColor": "rgba(255, 102, 170, 0.3)",
            "cost": 5000,
            "special": "cosmic"
        },
        {
            "id": "custom-example",
            "name": "Minha Skin",
            "color": "#ff3333",
            "type": "free",
            "glowColor": "rgba(255, 51, 51, 0.5)",
            "borderColor": "rgba(255, 51, 51, 0.3)",
            "cost": 0
        }
    ],
    "instructions": {
        "como_adicionar": [
            "1. Copie um dos blocos de skin acima",
            "2. Cole no final da lista (antes do último ])",
            "3. Mude os valores conforme desejado:",
            "   - id: nome único para sua skin (use hífen para espaços)",
            "   - name: nome que aparecerá no jogo",
            "   - color: cor em formato HEX (#RRGGBB)",
            "   - type: 'free' ou 'premium'",
            "   - cost: preço em moedas (0 para free)",
            "   - special: 'rainbow' ou 'cosmic' (opcional)",
            "4. Para cores com transparência (glowColor/borderColor):",
            "   - Use rgba(R, G, B, transparência)",
            "   - R, G, B são números de 0-255",
            "   - transparência é de 0.0 a 1.0"
        ],
        "exemplo_cores": {
            "vermelho": "#ff0000",
            "verde": "#00ff00",
            "azul": "#0000ff",
            "amarelo": "#ffff00",
            "roxo": "#9966ff",
            "rosa": "#ff66aa",
            "laranja": "#ff9900",
            "ciano": "#00ffff"
        }
    }
} 